streamlit_input_box/__init__.py
streamlit_input_box/frontend/build/asset-manifest.json
streamlit_input_box/frontend/build/bootstrap.min.css
streamlit_input_box/frontend/build/index.html
streamlit_input_box/frontend/build/static/css/main.a48e4cb6.css
streamlit_input_box/frontend/build/static/css/main.a48e4cb6.css.map
streamlit_input_box/frontend/build/static/js/main.9a3477f6.js
streamlit_input_box/frontend/build/static/js/main.9a3477f6.js.LICENSE.txt
streamlit_input_box/frontend/build/static/js/main.9a3477f6.js.map
streamlit_input_box/frontend/build/static/media/fontawesome-webfont.1e59d2330b4c6deb84b3.ttf
streamlit_input_box/frontend/build/static/media/fontawesome-webfont.20fd1704ea223900efa9.woff2
streamlit_input_box/frontend/build/static/media/fontawesome-webfont.8b43027f47b20503057d.eot
streamlit_input_box/frontend/build/static/media/fontawesome-webfont.c1e38fd9e0e74ba58f7a.svg
streamlit_input_box/frontend/build/static/media/fontawesome-webfont.f691f37e57f04c152e23.woff
streamlit_input_box-0.0.3.dist-info/LICENSE
streamlit_input_box-0.0.3.dist-info/METADATA
streamlit_input_box-0.0.3.dist-info/WHEEL
streamlit_input_box-0.0.3.dist-info/top_level.txt
streamlit_input_box-0.0.3.dist-info/RECORD
