Metadata-Version: 2.1
Name: streamlit_input_box
Version: 0.0.3
Summary: Streamlit component that allows you to edit text/code in a convenient text area.
Home-page: https://github.com/B4PT0R/streamlit_input_box
Author: Baptiste Ferrand
Author-email: bferrand.maths@gmail.com
Requires-Python: >=3.7
License-File: LICENSE
Requires-Dist: streamlit >=0.63
